tui_executor/__init__.py
tui_executor/__main__.py
tui_executor/app.py
tui_executor/app.tcss
tui_executor/arguments.py
tui_executor/client.py
tui_executor/demo.py
tui_executor/dialogs.py
tui_executor/exec.py
tui_executor/funcpars.py
tui_executor/functions.py
tui_executor/help.md
tui_executor/help.py
tui_executor/kernel.py
tui_executor/master.py
tui_executor/modules.py
tui_executor/panels.py
tui_executor/runnables.py
tui_executor/script_app.py
tui_executor/tasks.py
tui_executor/transforms.py
tui_executor/utils.py
tui_executor/utypes.py
tui_executor/version.py
tui_executor/view.py
tui_executor/demo/tasks/demo/__init__.py
tui_executor/demo/tasks/demo/function_names.py
tui_executor/demo/tasks/demo/immediate_run.py
tui_executor/demo/tasks/demo/run_types.py
tui_executor/demo/tasks/demo/simple_arguments.py
tui_executor/demo/tasks/demo/tooltips.py
tui_executor/demo/tasks/demo/var_name.py
tui_executor-0.4.1.dist-info/METADATA
tui_executor-0.4.1.dist-info/WHEEL
tui_executor-0.4.1.dist-info/entry_points.txt
tui_executor-0.4.1.dist-info/RECORD
