Metadata-Version: 2.3
Name: tui-executor
Version: 0.4.1
Summary: Execute Python code in an automatically generated TUI App.
Project-URL: documentation, https://rhuygen.github.io/tui-executor/
Project-URL: repository, https://github.com/rhuygen/tui-executor
Author-email: Rik Huygen <rik.huygen@kuleuven.be>
License: MIT
Keywords: TUI,execute,task
Classifier: Development Status :: 2 - Pre-Alpha
Classifier: Environment :: Console
Classifier: License :: OSI Approved :: MIT License
Classifier: Programming Language :: Python :: 3.8
Classifier: Programming Language :: Python :: 3.9
Classifier: Programming Language :: Python :: 3.10
Classifier: Programming Language :: Python :: 3.11
Classifier: Programming Language :: Python :: 3.12
Classifier: Topic :: Utilities
Requires-Python: >=3.8
Requires-Dist: distro
Requires-Dist: executor
Requires-Dist: ipykernel>=6.15
Requires-Dist: ipython>=8
Requires-Dist: jupyter-client>=8.6
Requires-Dist: jupyter-console>=6.6
Requires-Dist: jupyter-core>=5.7
Requires-Dist: pyyaml
Requires-Dist: rich>=13
Requires-Dist: textual
Provides-Extra: dev
Requires-Dist: textual-dev; extra == 'dev'
Provides-Extra: test
Requires-Dist: faker; extra == 'test'
Requires-Dist: lorem-text; extra == 'test'
Requires-Dist: pytest; extra == 'test'
Requires-Dist: pytest-order; extra == 'test'
